markerlib/__init__.py
markerlib/markers.py
markerlib/test.py
markerlib-0.6.0.dist-info/top_level.txt
markerlib-0.6.0.dist-info/METADATA
markerlib-0.6.0.dist-info/metadata.json
markerlib-0.6.0.dist-info/WHEEL
markerlib-0.6.0.dist-info/RECORD
