Metadata-Version: 1.1
Name: markerlib
Version: 0.6.0
Summary: A compiler for PEP 345 environment markers.
Home-page: http://bitbucket.org/dholth/markerlib/
Author: Daniel Holth
Author-email: dholth@fastmail.fm
License: MIT
Keywords: packaging pep345
Platform: UNKNOWN
Classifier: Development Status :: 4 - Beta
Classifier: Intended Audience :: Developers
Classifier: Programming Language :: Python
Classifier: Programming Language :: Python :: 2
Classifier: Programming Language :: Python :: 3
Classifier: Programming Language :: Python :: 2.4
Classifier: Programming Language :: Python :: 2.5
Classifier: Programming Language :: Python :: 2.6
Classifier: Programming Language :: Python :: 2.7
Classifier: Programming Language :: Python :: 3.2
Classifier: Programming Language :: Python :: 3.3
